{"cameraMode":{"drawMode":0,"name":"Shaded","section":"Shading Mode"},"sceneLighting":true,"audioPlay":false,"sceneViewState":{"m_AlwaysRefresh":false,"showFog":true,"showSkybox":true,"showFlares":true,"showImageEffects":true,"showParticleSystems":true,"showVisualEffectGraphs":true,"m_FxEnabled":true},"in2DMode":false,"pivot":{"x":-24.489282608032228,"y":-77.74072265625,"z":495.8520202636719},"rotation":{"x":-0.10630112886428833,"y":0.011929099448025227,"z":-0.0012750370660796762,"w":-0.9942632913589478},"size":268.04827880859377,"orthographic":false}